odoo/addons/purchase_order_qty_by_product_category/README.rst
odoo/addons/purchase_order_qty_by_product_category/__init__.py
odoo/addons/purchase_order_qty_by_product_category/__manifest__.py
odoo/addons/purchase_order_qty_by_product_category/i18n/es.po
odoo/addons/purchase_order_qty_by_product_category/i18n/fr.po
odoo/addons/purchase_order_qty_by_product_category/i18n/purchase_order_qty_by_product_category.pot
odoo/addons/purchase_order_qty_by_product_category/models/__init__.py
odoo/addons/purchase_order_qty_by_product_category/models/purchase_order.py
odoo/addons/purchase_order_qty_by_product_category/models/purchase_order_line.py
odoo/addons/purchase_order_qty_by_product_category/models/purchase_order_qty_by_product_category.py
odoo/addons/purchase_order_qty_by_product_category/models/res_company.py
odoo/addons/purchase_order_qty_by_product_category/models/res_config_settings.py
odoo/addons/purchase_order_qty_by_product_category/readme/CONTRIBUTORS.rst
odoo/addons/purchase_order_qty_by_product_category/readme/DESCRIPTION.rst
odoo/addons/purchase_order_qty_by_product_category/readme/USAGE.rst
odoo/addons/purchase_order_qty_by_product_category/security/ir.model.access.csv
odoo/addons/purchase_order_qty_by_product_category/static/description/icon.png
odoo/addons/purchase_order_qty_by_product_category/static/description/index.html
odoo/addons/purchase_order_qty_by_product_category/tests/__init__.py
odoo/addons/purchase_order_qty_by_product_category/tests/test_purchase_order_qty_by_product_category.py
odoo/addons/purchase_order_qty_by_product_category/views/purchase_order.xml
odoo/addons/purchase_order_qty_by_product_category/views/res_config_settings.xml
odoo_addon_purchase_order_qty_by_product_category-15.0.1.0.0.8.dist-info/METADATA
odoo_addon_purchase_order_qty_by_product_category-15.0.1.0.0.8.dist-info/WHEEL
odoo_addon_purchase_order_qty_by_product_category-15.0.1.0.0.8.dist-info/top_level.txt
odoo_addon_purchase_order_qty_by_product_category-15.0.1.0.0.8.dist-info/RECORD
